lins_restapi/__init__.py
lins_restapi/http/__init__.py
lins_restapi/http/envelope_middleware.py
lins_restapi/http/exception.py
lins_restapi/http/log_middleware.py
lins_restapi/http/pagination.py
lins_restapi/schemas/__init__.py
lins_restapi/schemas/swagger.py
lins_restapi-2.0.2.26.dist-info/METADATA
lins_restapi-2.0.2.26.dist-info/WHEEL
lins_restapi-2.0.2.26.dist-info/top_level.txt
lins_restapi-2.0.2.26.dist-info/RECORD
