Metadata-Version: 2.1
Name: lins-restapi
Version: 2.0.2.26
Summary: Classes e utilitarios para uso em apis rest com django.
Home-page: https://bitbucket.org/grupolinsferrao/pypck-lins-restapi/
Author: TI Sistemas
Author-email: ti.sistemas@grupolinsferrao.com.br
License: MIT
